Simpycity-2.0.1.dist-info/DESCRIPTION.rst
Simpycity-2.0.1.dist-info/METADATA
Simpycity-2.0.1.dist-info/RECORD
Simpycity-2.0.1.dist-info/WHEEL
Simpycity-2.0.1.dist-info/metadata.json
Simpycity-2.0.1.dist-info/top_level.txt
simpycity/__init__.py
simpycity/config.py
simpycity/core.py
simpycity/handle.py
simpycity/model.py
simpycity/test/__init__.py
simpycity/test/test.ini
simpycity/test/test_core.py
simpycity/test/test_handle.py
simpycity/test/sql/test.sql
simpycity/test/sql/test_unload.sql
