Metadata-Version: 2.0
Name: Simpycity
Version: 2.0.1
Summary: A database-respecting object-relational mapper for PostgreSQL.
Home-page: https://github.com/commandprompt/Simpycity
Author: Command Prompt, Inc.
Author-email: support@commandprompt.com
License: LGPL
Download-URL: https://github.com/commandprompt/Simpycity/releases/tag/2.0.1
Keywords: orm postgresql
Platform: UNKNOWN
Classifier: Development Status :: 5 - Production/Stable
Classifier: Intended Audience :: Developers
Classifier: License :: OSI Approved :: GNU Library or Lesser General Public License (LGPL)
Classifier: Operating System :: OS Independent
Classifier: Topic :: Software Development :: Libraries :: Python Modules
Classifier: Topic :: Database
Classifier: Programming Language :: Python :: 2
Classifier: Programming Language :: Python :: 2.7
Classifier: Programming Language :: Python :: 3
Classifier: Programming Language :: Python :: 3.3
Classifier: Programming Language :: Python :: 3.4
Classifier: Programming Language :: Python :: 3.5
Classifier: Natural Language :: English
Requires-Dist: future
Requires-Dist: psycopg2 (>=2.5)
